main.py
mp_server-0.1.0.dist-info/METADATA
mp_server-0.1.0.dist-info/WHEEL
mp_server-0.1.0.dist-info/top_level.txt
mp_server-0.1.0.dist-info/RECORD
